hmtest/__init__.py
hmtest/console.py
hmtest/wikipedia.py
hmtest-0.1.0.dist-info/entry_points.txt
hmtest-0.1.0.dist-info/LICENSE
hmtest-0.1.0.dist-info/WHEEL
hmtest-0.1.0.dist-info/METADATA
hmtest-0.1.0.dist-info/RECORD
